pyjail/__init__.py
pyjail/main.py
tests/__init__.py
tests/test_main.py
PyJail-0.1.4.dist-info/LICENSE.txt
PyJail-0.1.4.dist-info/METADATA
PyJail-0.1.4.dist-info/WHEEL
PyJail-0.1.4.dist-info/top_level.txt
PyJail-0.1.4.dist-info/RECORD
