Metadata-Version: 2.1
Name: PyJail
Version: 0.1.4
Summary: A Python module for sandboxing code execution.
Home-page: https://github.com/mrigankpawagi/PyJail
Author: Mrigank Pawagi
Author-email: Mrigank Pawagi <mrigankpawagi@gmail.com>
License: MIT
Project-URL: Homepage, https://github.com/mrigankpawagi/PyJail
Classifier: Programming Language :: Python :: 3
Classifier: License :: OSI Approved :: MIT License
Classifier: Operating System :: POSIX :: Linux
Requires-Python: >=3.6
License-File: LICENSE.txt
